conversion/__init__.py
conversion/_version.py
conversion/base64.py
conversion/boolean.py
conversion/compat.py
conversion/delta.py
conversion/json.py
conversion/list.py
conversion-0.0.9.dist-info/licenses/LICENSE
conversion-0.0.9.dist-info/METADATA
conversion-0.0.9.dist-info/WHEEL
conversion-0.0.9.dist-info/top_level.txt
conversion-0.0.9.dist-info/RECORD
