Metadata-Version: 2.4
Name: conversion
Version: 0.0.9
Summary: Utility functions to convert strings to Python types
Author-email: Roberto Aguilar <r@rreboto.com>
License: Apache License
License-File: LICENSE
Dynamic: license-file
